{
	"name": "qscript",
	"description": "A Simple Scripting Language",
	"copyright": "Copyright © 2016-2021, Nafees Hassan",
	"license":"MIT",
	"authors": ["Nafees Hassan"],
	"dependencies": {
		"utils": "~>0.3.7",
		"navm": "~>1.1.4"
	},"configurations": [
		{
			"name": "default",
			"targetType": "library",
			"targetName": "qscript"
		},
		{
			"name": "qsDemo",
			"targetType": "executable",
			"targetName": "demo",
			"versions": ["qscriptdemo"]
		},
		{
			"name": "qsCompiler",
			"targetType": "executable",
			"targetName": "compiler",
			"versions": ["compiler"]
		}
	]
}
